streamlit_feedback/__init__.py
streamlit_feedback/examples.py
streamlit_feedback/frontend/build/asset-manifest.json
streamlit_feedback/frontend/build/bootstrap.min.css
streamlit_feedback/frontend/build/index.html
streamlit_feedback/frontend/build/static/js/main.01237b88.js
streamlit_feedback/frontend/build/static/js/main.01237b88.js.LICENSE.txt
streamlit_feedback/frontend/build/static/js/main.01237b88.js.map
streamlit_feedback/frontend/build/static/js/main.0dc21b88.js
streamlit_feedback/frontend/build/static/js/main.0dc21b88.js.LICENSE.txt
streamlit_feedback/frontend/build/static/js/main.0dc21b88.js.map
streamlit_feedback/frontend/build/static/js/main.225c7a52.js
streamlit_feedback/frontend/build/static/js/main.225c7a52.js.LICENSE.txt
streamlit_feedback/frontend/build/static/js/main.225c7a52.js.map
streamlit_feedback/frontend/build/static/js/main.2e4a070f.js
streamlit_feedback/frontend/build/static/js/main.2e4a070f.js.LICENSE.txt
streamlit_feedback/frontend/build/static/js/main.2e4a070f.js.map
streamlit_feedback/frontend/build/static/js/main.311d8454.js
streamlit_feedback/frontend/build/static/js/main.311d8454.js.LICENSE.txt
streamlit_feedback/frontend/build/static/js/main.311d8454.js.map
streamlit_feedback/frontend/build/static/js/main.3258be68.js
streamlit_feedback/frontend/build/static/js/main.3258be68.js.LICENSE.txt
streamlit_feedback/frontend/build/static/js/main.3258be68.js.map
streamlit_feedback/frontend/build/static/js/main.57837706.js
streamlit_feedback/frontend/build/static/js/main.57837706.js.LICENSE.txt
streamlit_feedback/frontend/build/static/js/main.57837706.js.map
streamlit_feedback/frontend/build/static/js/main.8a7e8c93.js
streamlit_feedback/frontend/build/static/js/main.8a7e8c93.js.LICENSE.txt
streamlit_feedback/frontend/build/static/js/main.8a7e8c93.js.map
streamlit_feedback/frontend/build/static/js/main.d715fd8f.js
streamlit_feedback/frontend/build/static/js/main.d715fd8f.js.LICENSE.txt
streamlit_feedback-0.1.4.dist-info/LICENSE
streamlit_feedback-0.1.4.dist-info/METADATA
streamlit_feedback-0.1.4.dist-info/WHEEL
streamlit_feedback-0.1.4.dist-info/top_level.txt
streamlit_feedback-0.1.4.dist-info/RECORD
