Metadata-Version: 2.1
Name: streamlit-feedback
Version: 0.1.4
Summary: Streamlit component that allows you to collect user feedback in your apps
Home-page: 
Author: Jeff Kayne
Author-email: jeff.kayne@trubrics.com
Classifier: Intended Audience :: Developers
Classifier: License :: OSI Approved :: MIT License
Classifier: Programming Language :: Python :: 3.7
Classifier: Programming Language :: Python :: 3.8
Classifier: Programming Language :: Python :: 3.9
Classifier: Programming Language :: Python :: 3.10
Classifier: Programming Language :: Python :: 3.11
Requires-Python: >=3.7
License-File: LICENSE
